prepareImage/__init__.py
prepareImage/__main__.py
prepareImage/dataset.py
prepareImage/line_canny.py
prepareImage/line_hed.py
prepareImage/prepare_data.py
prepareImage-0.0.5.dist-info/LICENSE
prepareImage-0.0.5.dist-info/METADATA
prepareImage-0.0.5.dist-info/WHEEL
prepareImage-0.0.5.dist-info/top_level.txt
prepareImage-0.0.5.dist-info/RECORD
