Metadata-Version: 2.1
Name: prepareImage
Version: 0.0.5
Summary: Flexible and Easy. We perform a package that help you build your own image dataset. Specially, it's easy to add your own prepare function
Author-email: Khang Nguyen <duncannguyen2k@gmail.com>
Project-URL: Homepage, https://github.com/Khoa-Hoc-Du-Lieu/PrepareImage-Custom-Your-Our-Image-Dataset
Project-URL: Bug Tracker, https://github.com/Khoa-Hoc-Du-Lieu/PrepareImage-Custom-Your-Our-Image-Dataset/issues
Classifier: Programming Language :: Python :: 3
Classifier: License :: OSI Approved :: Apache Software License
Classifier: Operating System :: OS Independent
Requires-Python: >=3.7
License-File: LICENSE
